{"destinationZipList":[{"r":["005","098"],"z":"8"},{"r":["100","212"],"z":"8"},{"r":["214","268"],"z":"8"},{"r":["270","342"],"z":"8"},{"r":"344","z":"8"},{"r":["346","347"],"z":"8"},{"r":["349","352"],"z":"8"},{"r":["354","418"],"z":"8"},{"r":["420","427"],"z":"8"},{"r":["430","516"],"z":"8"},{"r":["520","528"],"z":"8"},{"r":["530","532"],"z":"8"},{"r":["534","535"],"z":"8"},{"r":["537","551"],"z":"8"},{"r":["553","567"],"z":"8"},{"r":["570","577"],"z":"8"},{"r":["580","588"],"z":"8"},{"r":["590","620"],"z":"8"},{"r":["622","631"],"z":"8"},{"r":["633","641"],"z":"8"},{"r":["644","658"],"z":"8"},{"r":["660","662"],"z":"8"},{"r":["664","681"],"z":"8"},{"r":["683","693"],"z":"8"},{"r":["700","701"],"z":"8"},{"r":["703","708"],"z":"8"},{"r":["710","714"],"z":"8"},{"r":["716","731"],"z":"8"},{"r":["733","741"],"z":"8"},{"r":["743","770"],"z":"8"},{"r":["772","816"],"z":"8"},{"r":["820","838"],"z":"8"},{"r":["840","847"],"z":"8"},{"r":["850","853"],"z":"8"},{"r":["855","857"],"z":"8"},{"r":["859","860"],"z":"8"},{"r":["863","865"],"z":"8"},{"r":["870","871"],"z":"8"},{"r":["873","885"],"z":"8"},{"r":["889","891"],"z":"8"},{"r":["893","895"],"z":"8"},{"r":["897","898"],"z":"8"},{"r":["900","908"],"z":"8"},{"r":["910","928"],"z":"8"},{"r":["930","961"],"z":"8"},{"r":["962","969"],"z":"1"},{"r":["970","986"],"z":"8"},{"r":["988","999"],"z":"8"}],"exceptionList":[]}